<Alloy>
	<NavigationWindow id="exNavWin">
	<Window id="workoutWinId" class="container" height="100%" backgroundImage="texture.jpg">
	<View layout="vertical">
		<Label bottom="20" top="5" color="black">Exercises to make you Swole today</Label>
		<TableView id="workoutsTable" class="workoutTable" height="SIZE" backgroundColor="transparent">		
		</TableView>
		<Button id="btnWorkout" top="10" title="Start Upper Body Workout" onClick="showUpperBodyWorkout"></Button>
	</View>
	</Window>
	</NavigationWindow>
</Alloy>